Nvmpy/__init__.py
Nvmpy/game.py
Nvmpy/hp.py
Nvmpy/nn.py
Nvmpy-0.2.4.dist-info/METADATA
Nvmpy-0.2.4.dist-info/WHEEL
Nvmpy-0.2.4.dist-info/top_level.txt
Nvmpy-0.2.4.dist-info/RECORD
