Metadata-Version: 2.1
Name: Nvmpy
Version: 0.2.4
Summary: A library to fetch categorized code snippets.
Home-page: https://github.com/yourusername/my_library
Author: A
Classifier: Programming Language :: Python :: 3
Classifier: Operating System :: OS Independent
Requires-Python: >=3.6
